{
	"disclaimer": "This data is collected from Google Calculator and provided free of charge for informational purposes only, with no guarantee whatsoever of accuracy, validity, availability or fitness for any purpose; use at your own risk. Other than that - have fun, and please share/watch/fork if you think data like this should be free!",
	"license": "http://www.opensource.org/licenses/GPL-3.0",
	"timestamp": 1322105331,
	"base": "USD",
	"rates": {
		"AED": 3.67300014,
		"ANG": 1.75999944,
		"ARS": 4.2589982,
		"AUD": 1.03050289,
		"BGN": 1.46469928,
		"BHD": 0.376910465,
		"BND": 1.30929983,
		"BOB": 7.01001731,
		"BRL": 1.86699874,
		"BWP": 7.49625187,
		"CAD": 1.04740009,
		"CHF": 0.919497954,
		"CLP": 508.130081,
		"CNY": 6.35760242,
		"COP": 1934.23598,
		"CRC": 500.751127,
		"CZK": 19.2318788,
		"DKK": 5.5692001,
		"DOP": 38.2000153,
		"DZD": 74.4934446,
		"EGP": 6.00081611,
		"EUR": 0.748951468,
		"FJD": 1.89393939,
		"GBP": 0.643997939,
		"HKD": 7.79447528,
		"HNL": 18.9100261,
		"HRK": 5.61359388,
		"HUF": 232.396003,
		"IDR": 9090.90909,
		"ILS": 3.77099501,
		"INR": 52.2602561,
		"JMD": 85.6531049,
		"JOD": 0.70899861,
		"JPY": 77.1426367,
		"KES": 90.3016074,
		"KRW": 1157.40741,
		"KWD": 0.276749959,
		"KYD": 0.820001476,
		"KZT": 147.275405,
		"LBP": 1506.0241,
		"LKR": 113.765643,
		"LTL": 2.58570313,
		"LVL": 0.525400487,
		"MAD": 8.37051236,
		"MDL": 11.8480605,
		"MKD": 45.5103991,
		"MUR": 29.1996379,
		"MXN": 14.1254909,
		"MYR": 3.18750498,
		"NAD": 8.58988455,
		"NGN": 158.906722,
		"NIO": 22.860278,
		"NOK": 5.86200832,
		"NPR": 82.8500414,
		"NZD": 1.35043889,
		"OMR": 0.385000385,
		"PEN": 2.70649912,
		"PGK": 2.22717149,
		"PHP": 43.449924,
		"PKR": 87.4508089,
		"PLN": 3.36630064,
		"PYG": 4424.77876,
		"QAR": 3.64130257,
		"RON": 3.26189777,
		"RSD": 77.5193798,
		"RUB": 31.3430497,
		"SAR": 3.75030471,
		"SCR": 12.7000254,
		"SEK": 6.91749504,
		"SGD": 1.30939926,
		"SLL": 4405.28634,
		"SVC": 8.74997813,
		"THB": 31.3695966,
		"TND": 1.46809894,
		"TRY": 1.8695992,
		"TTD": 6.37498964,
		"TWD": 30.3849777,
		"TZS": 1706.48464,
		"UAH": 7.99149705,
		"UGX": 2570.69409,
		"USD": 1,
		"UYU": 19.9001015,
		"UZS": 1769.9115,
		"VND": 20833.3333,
		"YER": 217.864924,
		"ZAR": 8.57066945,
		"ZMK": 5102.04082
	}
}